ate/__init__.py
ate/base.py
tf_ate-1.0.5.dist-info/LICENSE.txt
tf_ate-1.0.5.dist-info/METADATA
tf_ate-1.0.5.dist-info/WHEEL
tf_ate-1.0.5.dist-info/top_level.txt
tf_ate-1.0.5.dist-info/RECORD
