Metadata-Version: 2.1
Name: tf-ate
Version: 1.0.5
Summary: Approximate Text Explanation
Home-page: https://github.com/tjarkpr/ate
Author: Tjark Prokoph
Author-email: tjark.prokoph@gmx.de
Project-URL: Issues, https://github.com/tjarkpr/ate/issues
Project-URL: Repository, https://github.com/tjarkpr/ate
Classifier: Programming Language :: Python :: 3
Classifier: License :: OSI Approved :: MIT License
Classifier: Operating System :: OS Independent
Requires-Python: >=3.10
License-File: LICENSE.txt
